langprotect_mcp_gateway/__init__.py
langprotect_mcp_gateway/gateway.py
langprotect_mcp_gateway/setup_helper.py
langprotect_mcp_gateway-1.2.5.dist-info/licenses/LICENSE
langprotect_mcp_gateway-1.2.5.dist-info/METADATA
langprotect_mcp_gateway-1.2.5.dist-info/WHEEL
langprotect_mcp_gateway-1.2.5.dist-info/entry_points.txt
langprotect_mcp_gateway-1.2.5.dist-info/top_level.txt
langprotect_mcp_gateway-1.2.5.dist-info/RECORD
