Metadata-Version: 2.4
Name: langprotect-mcp-gateway
Version: 1.2.5
Summary: Security gateway for Model Context Protocol (MCP) to protect AI tool interactions
Author-email: LangProtect Security Team <security@langprotect.com>
License: MIT
Project-URL: Homepage, https://www.langprotect.com/
Project-URL: Documentation, https://www.langprotect.com/docs
Project-URL: Repository, https://github.com/langprotect/mcp-gateway
Project-URL: Issues, https://github.com/langprotect/mcp-gateway/issues
Keywords: mcp,security,ai-security,langprotect,model-context-protocol
Classifier: Development Status :: 5 - Production/Stable
Classifier: Intended Audience :: Developers
Classifier: Topic :: Security
Classifier: License :: OSI Approved :: MIT License
Classifier: Programming Language :: Python :: 3
Classifier: Programming Language :: Python :: 3.11
Classifier: Programming Language :: Python :: 3.12
Requires-Python: >=3.8
License-File: LICENSE
Requires-Dist: requests>=2.31.0
Provides-Extra: dev
Requires-Dist: pytest>=7.0.0; extra == "dev"
Requires-Dist: black>=23.0.0; extra == "dev"
Requires-Dist: mypy>=1.0.0; extra == "dev"
Dynamic: license-file
